{
  "parent": "minecraft:recipes/root",
  "criteria": {
    "has_polished_moonstone": {
      "conditions": {
        "items": [
          {
            "items": [
              "vintagevibes:polished_moonstone"
            ]
          }
        ]
      },
      "trigger": "minecraft:inventory_changed"
    },
    "has_the_recipe": {
      "conditions": {
        "recipe": "vintagevibes:moonstone_tiles_from_polished_moonstone_stonecutting"
      },
      "trigger": "minecraft:recipe_unlocked"
    }
  },
  "requirements": [
    [
      "has_polished_moonstone",
      "has_the_recipe"
    ]
  ],
  "rewards": {
    "recipes": [
      "vintagevibes:moonstone_tiles_from_polished_moonstone_stonecutting"
    ]
  },
  "sends_telemetry_event": false
}